plog/__init__.py
plog/db.py
plog/components/__init__.py
plog/components/checkpoint.py
plog/components/objectframe.py
plog/components/task.py
plog/handlers/__init__.py
plog/handlers/log_handler.py
plog/handlers/object_handler.py
plog/models/__init__.py
plog/models/file_model.py
plog/models/log_model.py
plog_python-1.0.6.dist-info/METADATA
plog_python-1.0.6.dist-info/WHEEL
plog_python-1.0.6.dist-info/top_level.txt
plog_python-1.0.6.dist-info/RECORD
